README.md
setup.cfg
setup.py
sendpost.egg-info/PKG-INFO
sendpost.egg-info/SOURCES.txt
sendpost.egg-info/dependency_links.txt
sendpost.egg-info/requires.txt
sendpost.egg-info/top_level.txt
sendpost_python_sdk/__init__.py
sendpost_python_sdk/api_client.py
sendpost_python_sdk/configuration.py
sendpost_python_sdk/exceptions.py
sendpost_python_sdk/rest.py
sendpost_python_sdk/schemas.py
sendpost_python_sdk/apis/__init__.py
sendpost_python_sdk/apis/path_to_api.py
sendpost_python_sdk/apis/tag_to_api.py
sendpost_python_sdk/apis/paths/__init__.py
sendpost_python_sdk/apis/paths/subaccount_email_.py
sendpost_python_sdk/apis/paths/subaccount_email_template.py
sendpost_python_sdk/apis/paths/subaccount_suppression_.py
sendpost_python_sdk/apis/paths/subaccount_suppression_count.py
sendpost_python_sdk/apis/tags/__init__.py
sendpost_python_sdk/apis/tags/email_api.py
sendpost_python_sdk/apis/tags/suppression_api.py
sendpost_python_sdk/model/__init__.py
sendpost_python_sdk/model/attachment.py
sendpost_python_sdk/model/city.py
sendpost_python_sdk/model/copy_to.py
sendpost_python_sdk/model/count_stat.py
sendpost_python_sdk/model/delete_response.py
sendpost_python_sdk/model/device.py
sendpost_python_sdk/model/email_message.py
sendpost_python_sdk/model/email_response.py
sendpost_python_sdk/model/event_metadata.py
sendpost_python_sdk/model/model_from.py
sendpost_python_sdk/model/os.py
sendpost_python_sdk/model/q_email_message.py
sendpost_python_sdk/model/q_event.py
sendpost_python_sdk/model/r_suppression.py
sendpost_python_sdk/model/rd_suppression.py
sendpost_python_sdk/model/reply_to.py
sendpost_python_sdk/model/suppression.py
sendpost_python_sdk/model/suppression_email.py
sendpost_python_sdk/model/to.py
sendpost_python_sdk/model/user_agent.py
sendpost_python_sdk/model/webhook_event.py
sendpost_python_sdk/models/__init__.py
sendpost_python_sdk/paths/__init__.py
sendpost_python_sdk/paths/subaccount_email_/__init__.py
sendpost_python_sdk/paths/subaccount_email_/post.py
sendpost_python_sdk/paths/subaccount_email_template/__init__.py
sendpost_python_sdk/paths/subaccount_email_template/post.py
