Metadata-Version: 1.2
Name: sendpost
Version: 1.1.0
Summary: SendPost API
Home-page: https://github.com/sendpost/sendpost_python_sdk
Author: Sendpost
Author-email: dev@sendpost.io
License: UNKNOWN
Download-URL: https://github.com/sendpost/sendpost_python_sdk/archive/refs/tags/1.1.0.tar.gz
Keywords: OpenAPI,OpenAPI-Generator,SendPost API
Platform: UNKNOWN
Requires-Python: >=3.7
